[
    {
        "foto": "https://i.imgur.com/Vp1vfrB.png",
        "nome": "Artur Ricardo",
        "linkdin": "https://www.linkedin.com/feed/",
        "github:": "https://github.com/fga-eps-mds/2023.1-HEART-hub-fga-inovacao",
        "gitpage": "https://lucas13032003.github.io/"
    },
    {
        "foto": "https://i.imgur.com/3jmWu5f_d.jpg?maxwidth=520&shape=thumb&fidelity=high",
        "nome": "Esther Sena",
        "linkdin": "https://www.linkedin.com/feed/",
        "github:": "https://github.com/fga-eps-mds/2023.1-HEART-hub-fga-inovacao",
        "gitpage": "https://lucas13032003.github.io/"
    },
    {
        "foto": "https://i.imgur.com/CRAd1Fs_d.jpg?maxwidth=520&shape=thumb&fidelity=high",
        "nome": "Izabella Alves",
        "linkdin": "https://www.linkedin.com/feed/",
        "github:": "https://github.com/fga-eps-mds/2023.1-HEART-hub-fga-inovacao",
        "gitpage": "https://lucas13032003.github.io/"
    },
    {
        "foto": "https://i.imgur.com/il323f7_d.jpg?maxwidth=520&shape=thumb&fidelity=high",
        "nome": "Lucas Oliveira",
        "linkdin": "https://www.linkedin.com/feed/",
        "github:": "https://github.com/fga-eps-mds/2023.1-HEART-hub-fga-inovacao",
        "gitpage": "https://lucas13032003.github.io/"
    },
    {
        "foto": "https://i.imgur.com/GypqNGp_d.jpg?maxwidth=520&shape=thumb&fidelity=high",
        "nome": "Lucas Ribeiro",
        "linkdin": "https://www.linkedin.com/feed/",
        "github:": "https://github.com/fga-eps-mds/2023.1-HEART-hub-fga-inovacao",
        "gitpage": "https://lucas13032003.github.io/"
    },
    {
        "foto": "https://i.imgur.com/DAYNopP_d.jpg?maxwidth=520&shape=thumb&fidelity=high",
        "nome": "Lucas Víctor",
        "linkdin": "https://www.linkedin.com/public-profile/settings",
        "github:": "https://github.com/Lucas13032003",
        "gitpage": "https://lucas13032003.github.io/"
    },
    {
        "foto": "https://i.imgur.com/8812VFC_d.jpg?maxwidth=520&shape=thumb&fidelity=high",
        "nome": "Mariiana Siqueira",
        "linkdin": "https://www.linkedin.com/feed/",
        "github:": "https://github.com/fga-eps-mds/2023.1-HEART-hub-fga-inovacao",
        "gitpage": "https://lucas13032003.github.io/"
    }
]